py_miz_controller.cpython-310-x86_64-linux-gnu.so
mizcore-0.0.4.dist-info/LICENSE
mizcore-0.0.4.dist-info/METADATA
mizcore-0.0.4.dist-info/WHEEL
mizcore-0.0.4.dist-info/top_level.txt
mizcore-0.0.4.dist-info/RECORD
