Metadata-Version: 2.1
Name: mizcore
Version: 0.0.4
Summary: Mizar Core Library
Home-page: https://github.com/mimosa-project/mizcore
Author: Kazuhisa Nakasho
Author-email: kazuhisa.nakasho@gmail.com
Requires-Python: >=3.6
License-File: LICENSE
Provides-Extra: test
Requires-Dist: pytest (>=6.0) ; extra == 'test'
